{
  "step_id": "pp_proj_ch20",
  "book_id": "programming_python_fourth_edition",
  "chapter_num": 20,
  "title": "Advanced Search — Regex and Parsing",
  "description": "Add regex-based file content search to the file manager. Create a grep_files() function that searches file contents using regular expressions, returning structured results with filename, line number, and matching line text.",
  "builds_on": "pp_proj_ch19",
  "starter_code": "# File Manager CLI — Step 9: Advanced Search with Regex\n# Search inside file contents using regular expressions.\n\nimport os\nimport sys\nimport shutil\nimport fnmatch\nimport threading\nimport socket\nimport json\nimport shelve\nimport re\nfrom collections import deque\n\ndef get_system_info():\n    \"\"\"Return system information dict.\"\"\"\n    return {\n        'cwd': os.getcwd(),\n        'platform': sys.platform,\n        'python_version': sys.version,\n        'user': os.environ.get('USER', os.environ.get('USERNAME', '')),\n    }\n\nVALID_COMMANDS = ['list', 'search', 'info', 'help', 'copy', 'move', 'delete', 'bookmark', 'tree', 'grep']\n\ndef parse_command(args_list):\n    \"\"\"Parse a list of argument strings into a command dict.\"\"\"\n    if not args_list:\n        return {'command': 'help', 'args': []}\n    return {'command': args_list[0], 'args': args_list[1:]}\n\ndef list_directory(path='.'):\n    \"\"\"List contents of a directory with details.\"\"\"\n    entries = []\n    for name in os.listdir(path):\n        full_path = os.path.join(path, name)\n        is_dir = os.path.isdir(full_path)\n        size = 0 if is_dir else os.path.getsize(full_path)\n        ext = '' if is_dir else os.path.splitext(name)[1]\n        entries.append({'name': name, 'size': size, 'is_dir': is_dir, 'extension': ext})\n    return entries\n\ndef search_files(pattern, root_path='.'):\n    \"\"\"Search for files matching a pattern using threads.\"\"\"\n    results = []\n    lock = threading.Lock()\n    def search_dir(directory):\n        for dirpath, dirnames, filenames in os.walk(directory):\n            for fname in filenames:\n                if fnmatch.fnmatch(fname, pattern):\n                    with lock:\n                        results.append(os.path.join(dirpath, fname))\n    threads = []\n    for fname in os.listdir(root_path):\n        full = os.path.join(root_path, fname)\n        if os.path.isfile(full) and fnmatch.fnmatch(fname, pattern):\n            results.append(full)\n        elif os.path.isdir(full):\n            t = threading.Thread(target=search_dir, args=(full,))\n            threads.append(t)\n            t.start()\n    for t in threads:\n        t.join()\n    return results\n\nclass FileManager:\n    \"\"\"File operations: copy, move, delete, and batch rename.\"\"\"\n    def copy_file(self, src, dst):\n        try:\n            shutil.copy2(src, dst)\n            return f\"Copied {src} to {dst}\"\n        except Exception as e:\n            return f\"Error copying: {e}\"\n    def move_file(self, src, dst):\n        try:\n            shutil.move(src, dst)\n            return f\"Moved {src} to {dst}\"\n        except Exception as e:\n            return f\"Error moving: {e}\"\n    def delete_file(self, path):\n        try:\n            os.remove(path)\n            return f\"Deleted {path}\"\n        except Exception as e:\n            return f\"Error deleting: {e}\"\n    def batch_rename(self, directory, old_ext, new_ext):\n        renamed = []\n        for name in os.listdir(directory):\n            if name.endswith(old_ext):\n                old_path = os.path.join(directory, name)\n                new_name = name[:-len(old_ext)] + new_ext\n                new_path = os.path.join(directory, new_name)\n                os.rename(old_path, new_path)\n                renamed.append((name, new_name))\n        return renamed\n\nclass BookmarkManager:\n    \"\"\"Manage bookmarked directories and command history with shelve.\"\"\"\n    def __init__(self, db_path):\n        self.db_path = db_path\n    def add_bookmark(self, name, path):\n        with shelve.open(self.db_path) as db:\n            bookmarks = db.get('bookmarks', {})\n            bookmarks[name] = path\n            db['bookmarks'] = bookmarks\n    def list_bookmarks(self):\n        with shelve.open(self.db_path) as db:\n            return dict(db.get('bookmarks', {}))\n    def remove_bookmark(self, name):\n        with shelve.open(self.db_path) as db:\n            bookmarks = db.get('bookmarks', {})\n            if name in bookmarks:\n                del bookmarks[name]\n                db['bookmarks'] = bookmarks\n                return True\n            return False\n    def add_history(self, command_str):\n        with shelve.open(self.db_path) as db:\n            history = db.get('history', [])\n            history.append(command_str)\n            db['history'] = history\n    def get_history(self):\n        with shelve.open(self.db_path) as db:\n            return list(db.get('history', []))\n\nclass DirectoryTree:\n    \"\"\"A tree representation of a directory hierarchy.\"\"\"\n    def __init__(self, name, path, is_dir=True):\n        self.name = name\n        self.path = path\n        self.is_dir = is_dir\n        self.children = []\n    def build(self, max_depth=3, current_depth=0):\n        if not self.is_dir or current_depth >= max_depth:\n            return self\n        try:\n            for entry in os.listdir(self.path):\n                full = os.path.join(self.path, entry)\n                child = DirectoryTree(entry, full, os.path.isdir(full))\n                child.build(max_depth, current_depth + 1)\n                self.children.append(child)\n        except PermissionError:\n            pass\n        return self\n    def find(self, name):\n        queue = deque([self])\n        while queue:\n            node = queue.popleft()\n            if node.name == name:\n                return node\n            queue.extend(node.children)\n        return None\n    def get_path(self):\n        return self.path\n    def __repr__(self):\n        kind = 'DIR' if self.is_dir else 'FILE'\n        return f\"DirectoryTree({kind}: {self.name}, {len(self.children)} children)\"\n\ndef grep_files(pattern, directory, file_pattern='*'):\n    \"\"\"Search file contents for a regex pattern.\n\n    Args:\n        pattern: Regular expression pattern to search for.\n        directory: Directory to search in.\n        file_pattern: Optional glob pattern to filter files (e.g., '*.py').\n\n    Returns:\n        List of dicts, each with:\n        - 'file': file path (str)\n        - 'line_num': line number (int, 1-based)\n        - 'line': the matching line text, stripped (str)\n        - 'match': the matched text (str)\n    \"\"\"\n    # Your code here\n    return []\n\n# Test it\nimport tempfile\nwith tempfile.TemporaryDirectory() as tmpdir:\n    # Create test files\n    with open(os.path.join(tmpdir, 'hello.py'), 'w') as f:\n        f.write('# Hello world\\nprint(\"hello\")\\n')\n    results = grep_files(r'hello', tmpdir, '*.py')\n    for r in results:\n        print(f\"{r['file']}:{r['line_num']}: {r['line']}  (matched: {r['match']})\")\n",
  "test_code": "assert callable(grep_files), 'grep_files must be a callable function'\nimport inspect\nsrc = inspect.getsource(grep_files)\nassert 're' in sys.modules or 're.compile' in src or 're.search' in src or 're.findall' in src, 'grep_files should use the re module'\nimport tempfile, os\nwith tempfile.TemporaryDirectory() as tmpdir:\n    with open(os.path.join(tmpdir, 'test1.py'), 'w') as f:\n        f.write('import os\\nimport sys\\nprint(\"hello world\")\\n')\n    with open(os.path.join(tmpdir, 'test2.txt'), 'w') as f:\n        f.write('no match here\\nIMPORT something\\n')\n    results = grep_files(r'import', tmpdir)\n    assert isinstance(results, list), 'grep_files should return a list'\n    assert len(results) >= 2, f'Should find at least 2 matches for \"import\", got {len(results)}'\n    first = results[0]\n    assert isinstance(first, dict), 'Each result should be a dict'\n    assert 'file' in first, \"Result must have 'file' key\"\n    assert 'line_num' in first, \"Result must have 'line_num' key\"\n    assert 'line' in first, \"Result must have 'line' key\"\n    assert 'match' in first, \"Result must have 'match' key\"\n    assert isinstance(first['line_num'], int), 'line_num should be an int'\n    assert first['line_num'] >= 1, 'line_num should be 1-based'\n    py_results = grep_files(r'import', tmpdir, '*.py')\n    assert all(r['file'].endswith('.py') for r in py_results), 'With *.py filter, all results should be .py files'",
  "acceptance_criteria": [
    "grep_files() returns a list of dicts with file, line_num, line, match keys",
    "Uses re module for pattern matching",
    "line_num is 1-based",
    "file_pattern parameter filters which files to search",
    "Gracefully handles binary files or permission errors"
  ],
  "hints": [
    "Use re.compile(pattern) for efficiency",
    "Walk with os.walk(directory) to find files",
    "Filter files with fnmatch.fnmatch(fname, file_pattern)",
    "Read files with open(path, 'r', errors='ignore') to skip binary files",
    "Use enumerate(f, 1) for 1-based line numbers",
    "match.group() gives you the matched text from re.search()"
  ]
}
